aiojobs-stubs/__init__.pyi
aiojobs_protocols/__init__.py
aiojobs_protocols/py.typed
aiojobs_stubs-1.0.0.post0.dist-info/LICENSE
aiojobs_stubs-1.0.0.post0.dist-info/METADATA
aiojobs_stubs-1.0.0.post0.dist-info/WHEEL
aiojobs_stubs-1.0.0.post0.dist-info/top_level.txt
aiojobs_stubs-1.0.0.post0.dist-info/RECORD
