Metadata-Version: 2.1
Name: aiojobs-stubs
Version: 1.0.0.post0
Summary: External type annotations for the aiojobs library
Home-page: https://github.com/gleb-chipiga/aiojobs-stubs
Author: Gleb Chipiga
License: Apache 2
Keywords: asyncio,aiohttp,jobs,tasks,stubs,mypy
Platform: UNKNOWN
Classifier: Intended Audience :: Developers
Classifier: Programming Language :: Python
Classifier: Programming Language :: Python :: 3
Classifier: Programming Language :: Python :: 3.8
Classifier: Programming Language :: Python :: 3.9
Classifier: Programming Language :: Python :: 3.10
Classifier: License :: OSI Approved :: Apache Software License
Classifier: Operating System :: POSIX
Classifier: Operating System :: MacOS :: MacOS X
Classifier: Operating System :: Microsoft :: Windows
Classifier: Topic :: Internet
Classifier: Topic :: Software Development :: Libraries
Classifier: Topic :: Software Development :: Libraries :: Python Modules
Classifier: Framework :: AsyncIO
Requires-Python: >=3.8
License-File: LICENSE
